Workbook

Sheet Summary
A1: DCF Valuation Prototype - Company Comparison
A2: Discounted Cash Flow model applied to 3 real companies. Edit assumptions on each ticker's tab; this view updates automatically.
A4: Company | B4: Ticker | C4: Current Price ($) | D4: Intrinsic Value / Share ($) | E4: Upside / (Downside) | F4: Enterprise Value ($mm) | G4: Equity Value ($mm)
A5: Apple Inc. | B5: AAPL | C5: =AAPL!B34 -> 298 | D5: =AAPL!B33 -> 133.31946 | E5: =AAPL!B35 -> -0.55261927 | F5: =AAPL!B28 -> 2012861.6 | G5: =AAPL!B31 -> 1970461.6
A6: Microsoft Corp. | B6: MSFT | C6: =MSFT!B34 -> 378 | D6: =MSFT!B33 -> 285.5009 | E6: =MSFT!B35 -> -0.24470662 | F6: =MSFT!B28 -> 2131271.7 | G6: =MSFT!B31 -> 2121271.7
A7: Alphabet Inc. | B7: GOOGL | C7: =GOOGL!B34 -> 366 | D7: =GOOGL!B33 -> 175.87742 | E7: =GOOGL!B35 -> -0.5194606 | F7: =GOOGL!B28 -> 2060616.8 | G7: =GOOGL!B31 -> 2128116.8
A10: How this model works:
A11: 1. Each ticker's tab holds Inputs (blue) for FCF, growth, WACC, terminal growth, debt, cash, shares, and price.
A12: 2. FCF is projected 5 years forward, then discounted back to present value using the WACC.
A13: 3. A Terminal Value captures all cash flows beyond Year 5, using the Gordon Growth formula, and is also discounted to PV.
A14: 4. Enterprise Value = PV of 5-yr FCF + PV of Terminal Value. Equity Value = Enterprise Value - Debt + Cash.
A15: 5. Intrinsic Value per Share = Equity Value / Diluted Shares. Compared against the current market price to flag over/undervaluation.
A16: 6. Change any blue assumption cell on a company tab (e.g. WACC, growth rate) and every total recalculates automatically.
A18: Note: financial inputs are sourced from each company's most recent 10-K/annual report and recent market price (see source note on each tab).
A19: This is a simplified educational/portfolio model — production-grade DCFs would build a full 3-statement model and sensitivity tables.

Sheet AAPL
A1: Apple Inc. (AAPL) — DCF Valuation Prototype
A2: 5-year FCF projection, discounted to present value, plus terminal value (Gordon Growth).
A4: Inputs
A5: Base year Free Cash Flow ($mm) | B5: 98767
A6: Base year Revenue ($mm) | B6: 416200
A7: FCF growth rate (Yrs 1-5) | B7: 0.07
A8: Discount rate / WACC | B8: 0.09
A9: Terminal growth rate | B9: 0.03
A10: Cash & equivalents ($mm) | B10: 35900
A11: Total debt ($mm) | B11: 78300
A12: Diluted shares outstanding (mm) | B12: 14780
A13: Current share price ($) | B13: 298
A14: Source: Apple FY2025 10-K (FY ended Sep-2025); price ~Jun 2026
A16: Year | B16: Period (t) | C16: Projected FCF ($mm) | D16: Discount Factor | E16: PV of FCF ($mm)
A17: Year 1 | B17: 1 | C17: =$B$5*(1+$B$7) -> 105680.69 | D17: =1/(1+$B$8)^B17 -> 0.91743119 | E17: =C17*D17 -> 96954.761
A18: Year 2 | B18: 2 | C18: =C17*(1+$B$7) -> 113078.34 | D18: =1/(1+$B$8)^B18 -> 0.84167999 | E18: =C18*D18 -> 95175.775
A19: Year 3 | B19: 3 | C19: =C18*(1+$B$7) -> 120993.82 | D19: =1/(1+$B$8)^B19 -> 0.77218348 | E19: =C19*D19 -> 93429.431
A20: Year 4 | B20: 4 | C20: =C19*(1+$B$7) -> 129463.39 | D20: =1/(1+$B$8)^B20 -> 0.70842521 | E20: =C20*D20 -> 91715.129
A21: Year 5 | B21: 5 | C21: =C20*(1+$B$7) -> 138525.83 | D21: =1/(1+$B$8)^B21 -> 0.64993139 | E21: =C21*D21 -> 90032.283
A23: Terminal Value (at end of Year 5) | C23: =C21*(1+$B$9)/($B$8-$B$9) -> 2378026.7 | D23: =D21 -> 0.64993139 | E23: =C23*D23 -> 1545554.2
A25: Valuation Summary
A26: Sum of PV of 5-yr FCF ($mm) | B26: =SUM(E17:E21) -> 467307.38
A27: PV of Terminal Value ($mm) | B27: =E23 -> 1545554.2
A28: Enterprise Value ($mm) | B28: =B26+B27 -> 2012861.6
A29: Less: Total Debt ($mm) | B29: =-B11 -> -78300
A30: Add: Cash & Equivalents ($mm) | B30: =B10 -> 35900
A31: Equity Value ($mm) | B31: =B28+B29+B30 -> 1970461.6
A32: Diluted Shares Outstanding (mm) | B32: =B12 -> 14780
A33: Intrinsic Value per Share ($) | B33: =(B31*1)/B32 -> 133.31946
A34: Current Share Price ($) | B34: =B13 -> 298
A35: Upside / (Downside) to Intrinsic Value | B35: =B33/B34-1 -> -0.55261927
A37: Sensitivity: Intrinsic Value per Share ($)
A38: Rows = WACC, Columns = Terminal growth rate. Edit the blue axis values to widen/narrow the range.
A39: WACC \ Terminal g
B40: 0.02 | C40: 0.025 | D40: 0.03 | E40: 0.035 | F40: 0.04
A41: 0.08 | B41: =(SUMPRODUCT($B$5*(1+$B$7)^{1,2,3,4,5},(1+$A41)^-{1,2,3,4,5})+($B$5*(1+$B$7)^5*(1+B$40)/($A41-B$40))*(1+$A41)^-5-$B$11+$B$10)/$B$12 -> 138.06614 | C41: =(SUMPRODUCT($B$5*(1+$B$7)^{1,2,3,4,5},(1+$A41)^-{1,2,3,4,5})+($B$5*(1+$B$7)^5*(1+C$40)/($A41-C$40))*(1+$A41)^-5-$B$11+$B$10)/$B$12 -> 148.50414 | D41: =(SUMPRODUCT($B$5*(1+$B$7)^{1,2,3,4,5},(1+$A41)^-{1,2,3,4,5})+($B$5*(1+$B$7)^5*(1+D$40)/($A41-D$40))*(1+$A41)^-5-$B$11+$B$10)/$B$12 -> 161.02974 | E41: =(SUMPRODUCT($B$5*(1+$B$7)^{1,2,3,4,5},(1+$A41)^-{1,2,3,4,5})+($B$5*(1+$B$7)^5*(1+E$40)/($A41-E$40))*(1+$A41)^-5-$B$11+$B$10)/$B$12 -> 176.33881 | F41: =(SUMPRODUCT($B$5*(1+$B$7)^{1,2,3,4,5},(1+$A41)^-{1,2,3,4,5})+($B$5*(1+$B$7)^5*(1+F$40)/($A41-F$40))*(1+$A41)^-5-$B$11+$B$10)/$B$12 -> 195.47515
A42: 0.085 | B42: =(SUMPRODUCT($B$5*(1+$B$7)^{1,2,3,4,5},(1+$A42)^-{1,2,3,4,5})+($B$5*(1+$B$7)^5*(1+B$40)/($A42-B$40))*(1+$A42)^-5-$B$11+$B$10)/$B$12 -> 126.99567 | C42: =(SUMPRODUCT($B$5*(1+$B$7)^{1,2,3,4,5},(1+$A42)^-{1,2,3,4,5})+($B$5*(1+$B$7)^5*(1+C$40)/($A42-C$40))*(1+$A42)^-5-$B$11+$B$10)/$B$12 -> 135.66614 | D42: =(SUMPRODUCT($B$5*(1+$B$7)^{1,2,3,4,5},(1+$A42)^-{1,2,3,4,5})+($B$5*(1+$B$7)^5*(1+D$40)/($A42-D$40))*(1+$A42)^-5-$B$11+$B$10)/$B$12 -> 145.91307 | E42: =(SUMPRODUCT($B$5*(1+$B$7)^{1,2,3,4,5},(1+$A42)^-{1,2,3,4,5})+($B$5*(1+$B$7)^5*(1+E$40)/($A42-E$40))*(1+$A42)^-5-$B$11+$B$10)/$B$12 -> 158.20937 | F42: =(SUMPRODUCT($B$5*(1+$B$7)^{1,2,3,4,5},(1+$A42)^-{1,2,3,4,5})+($B$5*(1+$B$7)^5*(1+F$40)/($A42-F$40))*(1+$A42)^-5-$B$11+$B$10)/$B$12 -> 173.23819
A43: 0.09 | B43: =(SUMPRODUCT($B$5*(1+$B$7)^{1,2,3,4,5},(1+$A43)^-{1,2,3,4,5})+($B$5*(1+$B$7)^5*(1+B$40)/($A43-B$40))*(1+$A43)^-5-$B$11+$B$10)/$B$12 -> 117.51058 | C43: =(SUMPRODUCT($B$5*(1+$B$7)^{1,2,3,4,5},(1+$A43)^-{1,2,3,4,5})+($B$5*(1+$B$7)^5*(1+C$40)/($A43-C$40))*(1+$A43)^-5-$B$11+$B$10)/$B$12 -> 124.80698 | D43: =(SUMPRODUCT($B$5*(1+$B$7)^{1,2,3,4,5},(1+$A43)^-{1,2,3,4,5})+($B$5*(1+$B$7)^5*(1+D$40)/($A43-D$40))*(1+$A43)^-5-$B$11+$B$10)/$B$12 -> 133.31946 | E43: =(SUMPRODUCT($B$5*(1+$B$7)^{1,2,3,4,5},(1+$A43)^-{1,2,3,4,5})+($B$5*(1+$B$7)^5*(1+E$40)/($A43-E$40))*(1+$A43)^-5-$B$11+$B$10)/$B$12 -> 143.37965 | F43: =(SUMPRODUCT($B$5*(1+$B$7)^{1,2,3,4,5},(1+$A43)^-{1,2,3,4,5})+($B$5*(1+$B$7)^5*(1+F$40)/($A43-F$40))*(1+$A43)^-5-$B$11+$B$10)/$B$12 -> 155.45188
A44: 0.095 | B44: =(SUMPRODUCT($B$5*(1+$B$7)^{1,2,3,4,5},(1+$A44)^-{1,2,3,4,5})+($B$5*(1+$B$7)^5*(1+B$40)/($A44-B$40))*(1+$A44)^-5-$B$11+$B$10)/$B$12 -> 109.2937 | C44: =(SUMPRODUCT($B$5*(1+$B$7)^{1,2,3,4,5},(1+$A44)^-{1,2,3,4,5})+($B$5*(1+$B$7)^5*(1+C$40)/($A44-C$40))*(1+$A44)^-5-$B$11+$B$10)/$B$12 -> 115.50254 | D44: =(SUMPRODUCT($B$5*(1+$B$7)^{1,2,3,4,5},(1+$A44)^-{1,2,3,4,5})+($B$5*(1+$B$7)^5*(1+D$40)/($A44-D$40))*(1+$A44)^-5-$B$11+$B$10)/$B$12 -> 122.66658 | E44: =(SUMPRODUCT($B$5*(1+$B$7)^{1,2,3,4,5},(1+$A44)^-{1,2,3,4,5})+($B$5*(1+$B$7)^5*(1+E$40)/($A44-E$40))*(1+$A44)^-5-$B$11+$B$10)/$B$12 -> 131.02464 | F44: =(SUMPRODUCT($B$5*(1+$B$7)^{1,2,3,4,5},(1+$A44)^-{1,2,3,4,5})+($B$5*(1+$B$7)^5*(1+F$40)/($A44-F$40))*(1+$A44)^-5-$B$11+$B$10)/$B$12 -> 140.90234
A45: 0.1 | B45: =(SUMPRODUCT($B$5*(1+$B$7)^{1,2,3,4,5},(1+$A45)^-{1,2,3,4,5})+($B$5*(1+$B$7)^5*(1+B$40)/($A45-B$40))*(1+$A45)^-5-$B$11+$B$10)/$B$12 -> 102.10716 | C45: =(SUMPRODUCT($B$5*(1+$B$7)^{1,2,3,4,5},(1+$A45)^-{1,2,3,4,5})+($B$5*(1+$B$7)^5*(1+C$40)/($A45-C$40))*(1+$A45)^-5-$B$11+$B$10)/$B$12 -> 107.44179 | D45: =(SUMPRODUCT($B$5*(1+$B$7)^{1,2,3,4,5},(1+$A45)^-{1,2,3,4,5})+($B$5*(1+$B$7)^5*(1+D$40)/($A45-D$40))*(1+$A45)^-5-$B$11+$B$10)/$B$12 -> 113.53851 | E45: =(SUMPRODUCT($B$5*(1+$B$7)^{1,2,3,4,5},(1+$A45)^-{1,2,3,4,5})+($B$5*(1+$B$7)^5*(1+E$40)/($A45-E$40))*(1+$A45)^-5-$B$11+$B$10)/$B$12 -> 120.57318 | F45: =(SUMPRODUCT($B$5*(1+$B$7)^{1,2,3,4,5},(1+$A45)^-{1,2,3,4,5})+($B$5*(1+$B$7)^5*(1+F$40)/($A45-F$40))*(1+$A45)^-5-$B$11+$B$10)/$B$12 -> 128.78031

Sheet MSFT
A1: Microsoft Corp. (MSFT) — DCF Valuation Prototype
A2: 5-year FCF projection, discounted to present value, plus terminal value (Gordon Growth).
A4: Inputs
A5: Base year Free Cash Flow ($mm) | B5: 71600
A6: Base year Revenue ($mm) | B6: 281700
A7: FCF growth rate (Yrs 1-5) | B7: 0.12
A8: Discount rate / WACC | B8: 0.085
A9: Terminal growth rate | B9: 0.035
A10: Cash & equivalents ($mm) | B10: 30200
A11: Total debt ($mm) | B11: 40200
A12: Diluted shares outstanding (mm) | B12: 7430
A13: Current share price ($) | B13: 378
A14: Source: Microsoft FY2025 10-K (FY ended Jun-2025); price ~Jun 2026
A16: Year | B16: Period (t) | C16: Projected FCF ($mm) | D16: Discount Factor | E16: PV of FCF ($mm)
A17: Year 1 | B17: 1 | C17: =$B$5*(1+$B$7) -> 80192 | D17: =1/(1+$B$8)^B17 -> 0.92165899 | E17: =C17*D17 -> 73909.677
A18: Year 2 | B18: 2 | C18: =C17*(1+$B$7) -> 89815.04 | D18: =1/(1+$B$8)^B18 -> 0.84945529 | E18: =C18*D18 -> 76293.861
A19: Year 3 | B19: 3 | C19: =C18*(1+$B$7) -> 100592.84 | D19: =1/(1+$B$8)^B19 -> 0.7829081 | E19: =C19*D19 -> 78754.953
A20: Year 4 | B20: 4 | C20: =C19*(1+$B$7) -> 112663.99 | D20: =1/(1+$B$8)^B20 -> 0.72157428 | E20: =C20*D20 -> 81295.435
A21: Year 5 | B21: 5 | C21: =C20*(1+$B$7) -> 126183.66 | D21: =1/(1+$B$8)^B21 -> 0.66504542 | E21: =C21*D21 -> 83917.869
A23: Terminal Value (at end of Year 5) | C23: =C21*(1+$B$9)/($B$8-$B$9) -> 2612001.9 | D23: =D21 -> 0.66504542 | E23: =C23*D23 -> 1737099.9
A25: Valuation Summary
A26: Sum of PV of 5-yr FCF ($mm) | B26: =SUM(E17:E21) -> 394171.79
A27: PV of Terminal Value ($mm) | B27: =E23 -> 1737099.9
A28: Enterprise Value ($mm) | B28: =B26+B27 -> 2131271.7
A29: Less: Total Debt ($mm) | B29: =-B11 -> -40200
A30: Add: Cash & Equivalents ($mm) | B30: =B10 -> 30200
A31: Equity Value ($mm) | B31: =B28+B29+B30 -> 2121271.7
A32: Diluted Shares Outstanding (mm) | B32: =B12 -> 7430
A33: Intrinsic Value per Share ($) | B33: =(B31*1)/B32 -> 285.5009
A34: Current Share Price ($) | B34: =B13 -> 378
A35: Upside / (Downside) to Intrinsic Value | B35: =B33/B34-1 -> -0.24470662
A37: Sensitivity: Intrinsic Value per Share ($)
A38: Rows = WACC, Columns = Terminal growth rate. Edit the blue axis values to widen/narrow the range.
A39: WACC \ Terminal g
B40: 0.025 | C40: 0.03 | D40: 0.035 | E40: 0.04 | F40: 0.045
A41: 0.075 | B41: =(SUMPRODUCT($B$5*(1+$B$7)^{1,2,3,4,5},(1+$A41)^-{1,2,3,4,5})+($B$5*(1+$B$7)^5*(1+B$40)/($A41-B$40))*(1+$A41)^-5-$B$11+$B$10)/$B$12 -> 295.74443 | C41: =(SUMPRODUCT($B$5*(1+$B$7)^{1,2,3,4,5},(1+$A41)^-{1,2,3,4,5})+($B$5*(1+$B$7)^5*(1+C$40)/($A41-C$40))*(1+$A41)^-5-$B$11+$B$10)/$B$12 -> 324.00416 | D41: =(SUMPRODUCT($B$5*(1+$B$7)^{1,2,3,4,5},(1+$A41)^-{1,2,3,4,5})+($B$5*(1+$B$7)^5*(1+D$40)/($A41-D$40))*(1+$A41)^-5-$B$11+$B$10)/$B$12 -> 359.32881 | E41: =(SUMPRODUCT($B$5*(1+$B$7)^{1,2,3,4,5},(1+$A41)^-{1,2,3,4,5})+($B$5*(1+$B$7)^5*(1+E$40)/($A41-E$40))*(1+$A41)^-5-$B$11+$B$10)/$B$12 -> 404.74623 | F41: =(SUMPRODUCT($B$5*(1+$B$7)^{1,2,3,4,5},(1+$A41)^-{1,2,3,4,5})+($B$5*(1+$B$7)^5*(1+F$40)/($A41-F$40))*(1+$A41)^-5-$B$11+$B$10)/$B$12 -> 465.30279
A42: 0.08 | B42: =(SUMPRODUCT($B$5*(1+$B$7)^{1,2,3,4,5},(1+$A42)^-{1,2,3,4,5})+($B$5*(1+$B$7)^5*(1+B$40)/($A42-B$40))*(1+$A42)^-5-$B$11+$B$10)/$B$12 -> 267.86812 | C42: =(SUMPRODUCT($B$5*(1+$B$7)^{1,2,3,4,5},(1+$A42)^-{1,2,3,4,5})+($B$5*(1+$B$7)^5*(1+C$40)/($A42-C$40))*(1+$A42)^-5-$B$11+$B$10)/$B$12 -> 290.5645 | D42: =(SUMPRODUCT($B$5*(1+$B$7)^{1,2,3,4,5},(1+$A42)^-{1,2,3,4,5})+($B$5*(1+$B$7)^5*(1+D$40)/($A42-D$40))*(1+$A42)^-5-$B$11+$B$10)/$B$12 -> 318.30452 | E42: =(SUMPRODUCT($B$5*(1+$B$7)^{1,2,3,4,5},(1+$A42)^-{1,2,3,4,5})+($B$5*(1+$B$7)^5*(1+E$40)/($A42-E$40))*(1+$A42)^-5-$B$11+$B$10)/$B$12 -> 352.97954 | F42: =(SUMPRODUCT($B$5*(1+$B$7)^{1,2,3,4,5},(1+$A42)^-{1,2,3,4,5})+($B$5*(1+$B$7)^5*(1+F$40)/($A42-F$40))*(1+$A42)^-5-$B$11+$B$10)/$B$12 -> 397.56172
A43: 0.085 | B43: =(SUMPRODUCT($B$5*(1+$B$7)^{1,2,3,4,5},(1+$A43)^-{1,2,3,4,5})+($B$5*(1+$B$7)^5*(1+B$40)/($A43-B$40))*(1+$A43)^-5-$B$11+$B$10)/$B$12 -> 244.65259 | C43: =(SUMPRODUCT($B$5*(1+$B$7)^{1,2,3,4,5},(1+$A43)^-{1,2,3,4,5})+($B$5*(1+$B$7)^5*(1+C$40)/($A43-C$40))*(1+$A43)^-5-$B$11+$B$10)/$B$12 -> 263.22 | D43: =(SUMPRODUCT($B$5*(1+$B$7)^{1,2,3,4,5},(1+$A43)^-{1,2,3,4,5})+($B$5*(1+$B$7)^5*(1+D$40)/($A43-D$40))*(1+$A43)^-5-$B$11+$B$10)/$B$12 -> 285.5009 | E43: =(SUMPRODUCT($B$5*(1+$B$7)^{1,2,3,4,5},(1+$A43)^-{1,2,3,4,5})+($B$5*(1+$B$7)^5*(1+E$40)/($A43-E$40))*(1+$A43)^-5-$B$11+$B$10)/$B$12 -> 312.73311 | F43: =(SUMPRODUCT($B$5*(1+$B$7)^{1,2,3,4,5},(1+$A43)^-{1,2,3,4,5})+($B$5*(1+$B$7)^5*(1+F$40)/($A43-F$40))*(1+$A43)^-5-$B$11+$B$10)/$B$12 -> 346.77337
A44: 0.09 | B44: =(SUMPRODUCT($B$5*(1+$B$7)^{1,2,3,4,5},(1+$A44)^-{1,2,3,4,5})+($B$5*(1+$B$7)^5*(1+B$40)/($A44-B$40))*(1+$A44)^-5-$B$11+$B$10)/$B$12 -> 225.02195 | C44: =(SUMPRODUCT($B$5*(1+$B$7)^{1,2,3,4,5},(1+$A44)^-{1,2,3,4,5})+($B$5*(1+$B$7)^5*(1+C$40)/($A44-C$40))*(1+$A44)^-5-$B$11+$B$10)/$B$12 -> 240.44654 | D44: =(SUMPRODUCT($B$5*(1+$B$7)^{1,2,3,4,5},(1+$A44)^-{1,2,3,4,5})+($B$5*(1+$B$7)^5*(1+D$40)/($A44-D$40))*(1+$A44)^-5-$B$11+$B$10)/$B$12 -> 258.6756 | E44: =(SUMPRODUCT($B$5*(1+$B$7)^{1,2,3,4,5},(1+$A44)^-{1,2,3,4,5})+($B$5*(1+$B$7)^5*(1+E$40)/($A44-E$40))*(1+$A44)^-5-$B$11+$B$10)/$B$12 -> 280.55048 | F44: =(SUMPRODUCT($B$5*(1+$B$7)^{1,2,3,4,5},(1+$A44)^-{1,2,3,4,5})+($B$5*(1+$B$7)^5*(1+F$40)/($A44-F$40))*(1+$A44)^-5-$B$11+$B$10)/$B$12 -> 307.28645
A45: 0.095 | B45: =(SUMPRODUCT($B$5*(1+$B$7)^{1,2,3,4,5},(1+$A45)^-{1,2,3,4,5})+($B$5*(1+$B$7)^5*(1+B$40)/($A45-B$40))*(1+$A45)^-5-$B$11+$B$10)/$B$12 -> 208.20771 | C45: =(SUMPRODUCT($B$5*(1+$B$7)^{1,2,3,4,5},(1+$A45)^-{1,2,3,4,5})+($B$5*(1+$B$7)^5*(1+C$40)/($A45-C$40))*(1+$A45)^-5-$B$11+$B$10)/$B$12 -> 221.18896 | D45: =(SUMPRODUCT($B$5*(1+$B$7)^{1,2,3,4,5},(1+$A45)^-{1,2,3,4,5})+($B$5*(1+$B$7)^5*(1+D$40)/($A45-D$40))*(1+$A45)^-5-$B$11+$B$10)/$B$12 -> 236.33375 | E45: =(SUMPRODUCT($B$5*(1+$B$7)^{1,2,3,4,5},(1+$A45)^-{1,2,3,4,5})+($B$5*(1+$B$7)^5*(1+E$40)/($A45-E$40))*(1+$A45)^-5-$B$11+$B$10)/$B$12 -> 254.23214 | F45: =(SUMPRODUCT($B$5*(1+$B$7)^{1,2,3,4,5},(1+$A45)^-{1,2,3,4,5})+($B$5*(1+$B$7)^5*(1+F$40)/($A45-F$40))*(1+$A45)^-5-$B$11+$B$10)/$B$12 -> 275.7102

Sheet GOOGL
A1: Alphabet Inc. (GOOGL) — DCF Valuation Prototype
A2: 5-year FCF projection, discounted to present value, plus terminal value (Gordon Growth).
A4: Inputs
A5: Base year Free Cash Flow ($mm) | B5: 73300
A6: Base year Revenue ($mm) | B6: 402800
A7: FCF growth rate (Yrs 1-5) | B7: 0.13
A8: Discount rate / WACC | B8: 0.09
A9: Terminal growth rate | B9: 0.035
A10: Cash & equivalents ($mm) | B10: 126800
A11: Total debt ($mm) | B11: 59300
A12: Diluted shares outstanding (mm) | B12: 12100
A13: Current share price ($) | B13: 366
A14: Source: Alphabet FY2025 10-K/ARS (FY ended Dec-2025); price ~Jun 2026
A16: Year | B16: Period (t) | C16: Projected FCF ($mm) | D16: Discount Factor | E16: PV of FCF ($mm)
A17: Year 1 | B17: 1 | C17: =$B$5*(1+$B$7) -> 82829 | D17: =1/(1+$B$8)^B17 -> 0.91743119 | E17: =C17*D17 -> 75989.908
A18: Year 2 | B18: 2 | C18: =C17*(1+$B$7) -> 93596.77 | D18: =1/(1+$B$8)^B18 -> 0.84167999 | E18: =C18*D18 -> 78778.529
A19: Year 3 | B19: 3 | C19: =C18*(1+$B$7) -> 105764.35 | D19: =1/(1+$B$8)^B19 -> 0.77218348 | E19: =C19*D19 -> 81669.484
A20: Year 4 | B20: 4 | C20: =C19*(1+$B$7) -> 119513.72 | D20: =1/(1+$B$8)^B20 -> 0.70842521 | E20: =C20*D20 -> 84666.529
A21: Year 5 | B21: 5 | C21: =C20*(1+$B$7) -> 135050.5 | D21: =1/(1+$B$8)^B21 -> 0.64993139 | E21: =C21*D21 -> 87773.558
A23: Terminal Value (at end of Year 5) | C23: =C21*(1+$B$9)/($B$8-$B$9) -> 2541404.8 | D23: =D21 -> 0.64993139 | E23: =C23*D23 -> 1651738.8
A25: Valuation Summary
A26: Sum of PV of 5-yr FCF ($mm) | B26: =SUM(E17:E21) -> 408878.01
A27: PV of Terminal Value ($mm) | B27: =E23 -> 1651738.8
A28: Enterprise Value ($mm) | B28: =B26+B27 -> 2060616.8
A29: Less: Total Debt ($mm) | B29: =-B11 -> -59300
A30: Add: Cash & Equivalents ($mm) | B30: =B10 -> 126800
A31: Equity Value ($mm) | B31: =B28+B29+B30 -> 2128116.8
A32: Diluted Shares Outstanding (mm) | B32: =B12 -> 12100
A33: Intrinsic Value per Share ($) | B33: =(B31*1)/B32 -> 175.87742
A34: Current Share Price ($) | B34: =B13 -> 366
A35: Upside / (Downside) to Intrinsic Value | B35: =B33/B34-1 -> -0.5194606
A37: Sensitivity: Intrinsic Value per Share ($)
A38: Rows = WACC, Columns = Terminal growth rate. Edit the blue axis values to widen/narrow the range.
A39: WACC \ Terminal g
B40: 0.025 | C40: 0.03 | D40: 0.035 | E40: 0.04 | F40: 0.045
A41: 0.08 | B41: =(SUMPRODUCT($B$5*(1+$B$7)^{1,2,3,4,5},(1+$A41)^-{1,2,3,4,5})+($B$5*(1+$B$7)^5*(1+B$40)/($A41-B$40))*(1+$A41)^-5-$B$11+$B$10)/$B$12 -> 181.9076 | C41: =(SUMPRODUCT($B$5*(1+$B$7)^{1,2,3,4,5},(1+$A41)^-{1,2,3,4,5})+($B$5*(1+$B$7)^5*(1+C$40)/($A41-C$40))*(1+$A41)^-5-$B$11+$B$10)/$B$12 -> 196.82363 | D41: =(SUMPRODUCT($B$5*(1+$B$7)^{1,2,3,4,5},(1+$A41)^-{1,2,3,4,5})+($B$5*(1+$B$7)^5*(1+D$40)/($A41-D$40))*(1+$A41)^-5-$B$11+$B$10)/$B$12 -> 215.05433 | E41: =(SUMPRODUCT($B$5*(1+$B$7)^{1,2,3,4,5},(1+$A41)^-{1,2,3,4,5})+($B$5*(1+$B$7)^5*(1+E$40)/($A41-E$40))*(1+$A41)^-5-$B$11+$B$10)/$B$12 -> 237.8427 | F41: =(SUMPRODUCT($B$5*(1+$B$7)^{1,2,3,4,5},(1+$A41)^-{1,2,3,4,5})+($B$5*(1+$B$7)^5*(1+F$40)/($A41-F$40))*(1+$A41)^-5-$B$11+$B$10)/$B$12 -> 267.14204
A42: 0.085 | B42: =(SUMPRODUCT($B$5*(1+$B$7)^{1,2,3,4,5},(1+$A42)^-{1,2,3,4,5})+($B$5*(1+$B$7)^5*(1+B$40)/($A42-B$40))*(1+$A42)^-5-$B$11+$B$10)/$B$12 -> 166.656 | C42: =(SUMPRODUCT($B$5*(1+$B$7)^{1,2,3,4,5},(1+$A42)^-{1,2,3,4,5})+($B$5*(1+$B$7)^5*(1+C$40)/($A42-C$40))*(1+$A42)^-5-$B$11+$B$10)/$B$12 -> 178.85848 | D42: =(SUMPRODUCT($B$5*(1+$B$7)^{1,2,3,4,5},(1+$A42)^-{1,2,3,4,5})+($B$5*(1+$B$7)^5*(1+D$40)/($A42-D$40))*(1+$A42)^-5-$B$11+$B$10)/$B$12 -> 193.50145 | E42: =(SUMPRODUCT($B$5*(1+$B$7)^{1,2,3,4,5},(1+$A42)^-{1,2,3,4,5})+($B$5*(1+$B$7)^5*(1+E$40)/($A42-E$40))*(1+$A42)^-5-$B$11+$B$10)/$B$12 -> 211.39841 | F42: =(SUMPRODUCT($B$5*(1+$B$7)^{1,2,3,4,5},(1+$A42)^-{1,2,3,4,5})+($B$5*(1+$B$7)^5*(1+F$40)/($A42-F$40))*(1+$A42)^-5-$B$11+$B$10)/$B$12 -> 233.76961
A43: 0.09 | B43: =(SUMPRODUCT($B$5*(1+$B$7)^{1,2,3,4,5},(1+$A43)^-{1,2,3,4,5})+($B$5*(1+$B$7)^5*(1+B$40)/($A43-B$40))*(1+$A43)^-5-$B$11+$B$10)/$B$12 -> 153.76029 | C43: =(SUMPRODUCT($B$5*(1+$B$7)^{1,2,3,4,5},(1+$A43)^-{1,2,3,4,5})+($B$5*(1+$B$7)^5*(1+C$40)/($A43-C$40))*(1+$A43)^-5-$B$11+$B$10)/$B$12 -> 163.89731 | D43: =(SUMPRODUCT($B$5*(1+$B$7)^{1,2,3,4,5},(1+$A43)^-{1,2,3,4,5})+($B$5*(1+$B$7)^5*(1+D$40)/($A43-D$40))*(1+$A43)^-5-$B$11+$B$10)/$B$12 -> 175.87742 | E43: =(SUMPRODUCT($B$5*(1+$B$7)^{1,2,3,4,5},(1+$A43)^-{1,2,3,4,5})+($B$5*(1+$B$7)^5*(1+E$40)/($A43-E$40))*(1+$A43)^-5-$B$11+$B$10)/$B$12 -> 190.25355 | F43: =(SUMPRODUCT($B$5*(1+$B$7)^{1,2,3,4,5},(1+$A43)^-{1,2,3,4,5})+($B$5*(1+$B$7)^5*(1+F$40)/($A43-F$40))*(1+$A43)^-5-$B$11+$B$10)/$B$12 -> 207.82439
A44: 0.095 | B44: =(SUMPRODUCT($B$5*(1+$B$7)^{1,2,3,4,5},(1+$A44)^-{1,2,3,4,5})+($B$5*(1+$B$7)^5*(1+B$40)/($A44-B$40))*(1+$A44)^-5-$B$11+$B$10)/$B$12 -> 142.71543 | C44: =(SUMPRODUCT($B$5*(1+$B$7)^{1,2,3,4,5},(1+$A44)^-{1,2,3,4,5})+($B$5*(1+$B$7)^5*(1+C$40)/($A44-C$40))*(1+$A44)^-5-$B$11+$B$10)/$B$12 -> 151.24668 | D44: =(SUMPRODUCT($B$5*(1+$B$7)^{1,2,3,4,5},(1+$A44)^-{1,2,3,4,5})+($B$5*(1+$B$7)^5*(1+D$40)/($A44-D$40))*(1+$A44)^-5-$B$11+$B$10)/$B$12 -> 161.19981 | E44: =(SUMPRODUCT($B$5*(1+$B$7)^{1,2,3,4,5},(1+$A44)^-{1,2,3,4,5})+($B$5*(1+$B$7)^5*(1+E$40)/($A44-E$40))*(1+$A44)^-5-$B$11+$B$10)/$B$12 -> 172.9626 | F44: =(SUMPRODUCT($B$5*(1+$B$7)^{1,2,3,4,5},(1+$A44)^-{1,2,3,4,5})+($B$5*(1+$B$7)^5*(1+F$40)/($A44-F$40))*(1+$A44)^-5-$B$11+$B$10)/$B$12 -> 187.07795
A45: 0.1 | B45: =(SUMPRODUCT($B$5*(1+$B$7)^{1,2,3,4,5},(1+$A45)^-{1,2,3,4,5})+($B$5*(1+$B$7)^5*(1+B$40)/($A45-B$40))*(1+$A45)^-5-$B$11+$B$10)/$B$12 -> 133.15105 | C45: =(SUMPRODUCT($B$5*(1+$B$7)^{1,2,3,4,5},(1+$A45)^-{1,2,3,4,5})+($B$5*(1+$B$7)^5*(1+C$40)/($A45-C$40))*(1+$A45)^-5-$B$11+$B$10)/$B$12 -> 140.41129 | D45: =(SUMPRODUCT($B$5*(1+$B$7)^{1,2,3,4,5},(1+$A45)^-{1,2,3,4,5})+($B$5*(1+$B$7)^5*(1+D$40)/($A45-D$40))*(1+$A45)^-5-$B$11+$B$10)/$B$12 -> 148.78848 | E45: =(SUMPRODUCT($B$5*(1+$B$7)^{1,2,3,4,5},(1+$A45)^-{1,2,3,4,5})+($B$5*(1+$B$7)^5*(1+E$40)/($A45-E$40))*(1+$A45)^-5-$B$11+$B$10)/$B$12 -> 158.56188 | F45: =(SUMPRODUCT($B$5*(1+$B$7)^{1,2,3,4,5},(1+$A45)^-{1,2,3,4,5})+($B$5*(1+$B$7)^5*(1+F$40)/($A45-F$40))*(1+$A45)^-5-$B$11+$B$10)/$B$12 -> 170.11225
